{
  "session_id": "082601bf-1293-4e6c-89ff-813d7bcea79a",
  "start_time": "2025-10-10T00:03:08.441777",
  "system_version": "VeroBrix v2.0 - Sovereign Modular Intelligence",
  "provenance_version": "1.0",
  "entries": [
    {
      "entry_id": "27cc6a7b-4e08-478c-943e-4d52dd67d2a5",
      "timestamp": "2025-10-10T00:03:08.442498",
      "session_id": "082601bf-1293-4e6c-89ff-813d7bcea79a",
      "agent_name": "VeroBrixSystem",
      "human_operator": null,
      "system_version": "VeroBrix v2.0",
      "action_type": "system_init",
      "action_description": "VeroBrix Sovereign Intelligence System initialized - Session: 20251010_000308",
      "input_hash": null,
      "output_hash": null,
      "document_path": null,
      "legal_context": null,
      "sovereignty_score": null,
      "confidence_level": null,
      "parent_entry_id": null,
      "related_entries": [],
      "entry_hash": "deef286dbcb1477d"
    },
    {
      "entry_id": "18354223-e1bc-4efb-b83d-2cc12a83bbd4",
      "timestamp": "2025-10-10T00:03:08.442918",
      "session_id": "082601bf-1293-4e6c-89ff-813d7bcea79a",
      "agent_name": "System",
      "human_operator": null,
      "system_version": "VeroBrix v2.0",
      "action_type": "VeroBrix System",
      "action_description": "Initialized new session: 20251010_000308",
      "input_hash": null,
      "output_hash": null,
      "document_path": null,
      "legal_context": null,
      "sovereignty_score": null,
      "confidence_level": null,
      "parent_entry_id": null,
      "related_entries": [],
      "entry_hash": "3be6bacaf4a120c5"
    },
    {
      "entry_id": "1ae3ab5b-78d1-4a6a-b408-390114dda0e5",
      "timestamp": "2025-10-10T00:03:08.444103",
      "session_id": "082601bf-1293-4e6c-89ff-813d7bcea79a",
      "agent_name": "System",
      "human_operator": null,
      "system_version": "VeroBrix v2.0",
      "action_type": "VeroBrix System",
      "action_description": "Successfully loaded '/home/mrnam205/Desktop/Endorser2.0/verobrix_app/modules/../intake/sample_document.txt'",
      "input_hash": null,
      "output_hash": null,
      "document_path": null,
      "legal_context": null,
      "sovereignty_score": null,
      "confidence_level": null,
      "parent_entry_id": null,
      "related_entries": [],
      "entry_hash": "05832734d029d71d"
    },
    {
      "entry_id": "570f3e2c-098a-437b-98af-371588f9e58b",
      "timestamp": "2025-10-10T00:03:08.444498",
      "session_id": "082601bf-1293-4e6c-89ff-813d7bcea79a",
      "agent_name": "System",
      "human_operator": null,
      "system_version": "VeroBrix v2.0",
      "action_type": "VeroBrix System",
      "action_description": "Error during analysis: name 'log_provenance' is not defined",
      "input_hash": null,
      "output_hash": null,
      "document_path": null,
      "legal_context": null,
      "sovereignty_score": null,
      "confidence_level": null,
      "parent_entry_id": null,
      "related_entries": [],
      "entry_hash": "a70832b09d862c38"
    }
  ],
  "last_updated": "2025-10-10T00:03:08.444652"
}